[
  {
    "name": "Labret Clásico de Titanio",
    "stock": {
      "12mm": 8,
      "10mm": 1,
      "8mm": 7,
      "7mm": 2,
      "5mm": 3
    },
    "category": "Labrets",
    "body_parts": [
      "oreja",
      "labios"
    ],
    "price": 65.0,
    "sale_price": 59.9,
    "images": [
      "../static/img/products/labret/perla 3mm/foto 1.webp",
      "../static/img/products/labret/perla 3mm/foto 2.webp",
      "../static/img/products/labret/perla 3mm/foto 3.webp"
    ],
    "description": "Un labret versátil y seguro, hecho de Titanio Grado Implante.",
    "is_new": true,
    "on_sale": false,
    "material": "titanio",
    "popularity": 0,
    "rosca": "interna",
    "id": 1
  },
  {
    "name": "Labret Corona de Titanio con Zircón Blanco",
    "stock": {
      "1.2mm": 2
    },
    "category": "Labrets",
    "body_parts": [
      "oreja"
    ],
    "price": 110.0,
    "sale_price": 105.9,
    "images": [
      "../static/img/products/labret/helix/corona/foto 1 - 4.webp",
      "../static/img/products/labret/helix/corona/foto 1 - 2.webp",
      "../static/img/products/labret/helix/corona/foto 3 - 1.webp"
    ],
    "description": "Joya tipo labret hecha de Titanio Grado Implante de 4 cuerpos con Zirconitas incrustadas.",
    "is_new": true,
    "on_sale": false,
    "material": "titanio",
    "popularity": 0,
    "rosca": "interna",
    "id": 16
  },
  {
    "name": "Labret Laurel de Titanio con Zircón Blanco",
    "stock": {
      "1.6mm": 3
    },
    "category": "Labrets",
    "body_parts": [
      "oreja"
    ],
    "price": 110.0,
    "sale_price": 105.9,
    "images": [
      "../static/img/products/labret/helix/lateral/foto 1 - 4.webp",
      "../static/img/products/labret/helix/lateral/foto 1 - 3.webp",
      "../static/img/products/labret/helix/lateral/foto 3 - 1.webp"
    ],
    "description": "Joya tipo labret hecha de Titanio Grado Implante de 4 cuerpos con Zirconitas incrustadas.",
    "is_new": true,
    "on_sale": false,
    "material": "titanio",
    "popularity": 0,
    "rosca": "interna",
    "id": 17
  },
  {
    "name": "Labret Titanio 3 cuerpos Zircón Blanco",
    "stock": {
      "1.2mm": 2
    },
    "category": "Labrets",
    "body_parts": [
      "oreja"
    ],
    "price": 90.0,
    "sale_price": 85.9,
    "images": [
      "../static/img/products/labret/helix/3 cuerpos/foto 1 - 2.webp",
      "../static/img/products/labret/helix/3 cuerpos/foto 1 - 3.webp",
      "../static/img/products/labret/helix/3 cuerpos/foto 2 - 1.webp",
      "../static/img/products/labret/helix/3 cuerpos/foto 2 - 2.webp"
    ],
    "description": "Joya tipo Labret para piercing Helix hecha de Titanio Grado Implante con tres Zirconitas incrustadas.",
    "is_new": true,
    "on_sale": false,
    "material": "titanio",
    "popularity": 0,
    "rosca": "interna",
    "id": 13
  },
  {
    "name": "Labret Titanio con Zircón AB",
    "stock": {
      "8mm": 3
    },
    "category": "Labrets",
    "body_parts": [
      "oreja",
      "labios"
    ],
    "price": 80.0,
    "sale_price": 75.9,
    "images": [
      "../static/img/products/labret/zircon 3mm/ab/foto 1 - 1.webp",
      "../static/img/products/labret/zircon 3mm/ab/foto 1 - 2.webp",
      "../static/img/products/labret/zircon 3mm/ab/foto 3 - 1.webp",
      "../static/img/products/labret/zircon 3mm/ab/foto 3 - 2.webp"
    ],
    "description": "Joya tipo labret hecho de Titanio Grado Implante con una Zirconita incrustada.",
    "is_new": true,
    "on_sale": false,
    "material": "titanio",
    "popularity": 0,
    "rosca": "interna",
    "id": 3
  },
  {
    "name": "Labret con Púa de Titanio",
    "stock": {
      "12mm": 1,
      "10mm": 1,
      "8mm": 1,
      "7mm": 1
    },
    "category": "Labrets",
    "body_parts": [
      "oreja",
      "labios"
    ],
    "price": 65.0,
    "sale_price": 59.9,
    "images": [
      "../static/img/products/labret/pua 3mm/foto 1.webp",
      "../static/img/products/labret/pua 3mm/foto 2.webp",
      "../static/img/products/labret/pua 3mm/foto 3.webp"
    ],
    "description": "Un Joya moderna y segura, hecha de Titanio Grado Implante.",
    "is_new": true,
    "on_sale": false,
    "material": "titanio",
    "popularity": 0,
    "rosca": "interna",
    "id": 2
  },
  {
    "name": "Labret de Titanio con Amatista",
    "stock": {
      "8mm": 3
    },
    "category": "Labrets",
    "body_parts": [
      "oreja",
      "labios"
    ],
    "price": 80.0,
    "sale_price": 75.9,
    "images": [
      "../static/img/products/labret/zircon 3mm/purpura/foto 1 - 3.webp",
      "../static/img/products/labret/zircon 3mm/purpura/foto 3 - 2.webp"
    ],
    "description": "Joya tipo labret hecho de Titanio Grado Implante con una Amatista incrustada.",
    "is_new": true,
    "on_sale": false,
    "material": "titanio",
    "popularity": 0,
    "rosca": "interna",
    "id": 6
  },
  {
    "name": "Labret de Titanio con Obsidiana",
    "stock": {
      "8mm": 3
    },
    "category": "Labrets",
    "body_parts": [
      "oreja",
      "labios"
    ],
    "price": 80.0,
    "sale_price": 75.9,
    "images": [
      "../static/img/products/labret/zircon 3mm/obsidiana/foto 1 - 1.webp",
      "../static/img/products/labret/zircon 3mm/obsidiana/foto 1 - 3.webp",
      "../static/img/products/labret/zircon 3mm/obsidiana/foto 3 - 2.webp"
    ],
    "description": "Joya tipo labret hecho de titanio grado implante con una Obsidiana incrustada.",
    "is_new": true,
    "on_sale": false,
    "material": "titanio",
    "popularity": 0,
    "rosca": "interna",
    "id": 5
  },
  {
    "name": "Labret de Titanio con Zircón Blanco",
    "stock": {
      "8mm": 0
    },
    "category": "Labrets",
    "body_parts": [
      "oreja",
      "labios"
    ],
    "price": 80.0,
    "sale_price": 75.9,
    "images": [
      "../static/img/products/labret/zircon 3mm/blanco/foto 1 - 1.webp",
      "../static/img/products/labret/zircon 3mm/blanco/foto 3 - 2.webp"
    ],
    "description": "Joya labret hecho de Titanio Grado Implante con una Zirconita Blanca incrustada.",
    "is_new": true,
    "on_sale": false,
    "material": "titanio",
    "popularity": 0,
    "rosca": "interna",
    "id": 4
  },
  {
    "name": "Labret de Titanio con Zircón Rosa",
    "stock": {
      "8mm": 1
    },
    "category": "Labrets",
    "body_parts": [
      "oreja",
      "labios"
    ],
    "price": 80.0,
    "sale_price": 75.9,
    "images": [
      "../static/img/products/labret/zircon 3mm/rosa/foto 1 - 1.webp",
      "../static/img/products/labret/zircon 3mm/rosa/foto 3 - 1.webp"
    ],
    "description": "Joya tipo labret de Titanio Grado Implante con un Zircón Rosa incrustado.",
    "is_new": true,
    "on_sale": false,
    "material": "titanio",
    "popularity": 0,
    "rosca": "interna",
    "id": 7
  },
  {
    "name": "Labret de Titanio de 5 cuerpos de Aquamarine",
    "stock": {
      "1.2mm": 1
    },
    "category": "Labrets",
    "body_parts": [
      "oreja"
    ],
    "price": 120.0,
    "sale_price": 115.9,
    "images": [
      "../static/img/products/labret/helix/5 cuerpos/azul/foto 1 - 4.webp",
      "../static/img/products/labret/helix/5 cuerpos/azul/foto 1 - 2.webp",
      "../static/img/products/labret/helix/5 cuerpos/azul/foto 3 - 1.webp",
      "../static/img/products/labret/helix/5 cuerpos/azul/foto 3 - 2.webp"
    ],
    "description": "Joya tipo Labret para piercing Helix hecha de Titanio Grado Implante con 5 gemas de Aquamarine incrustadas.",
    "is_new": true,
    "on_sale": false,
    "material": "titanio",
    "popularity": 0,
    "rosca": "interna",
    "id": 14
  },
  {
    "name": "Labret de Titanio de 5 cuerpos de zircón Blanco",
    "stock": {
      "1.6mm": 2
    },
    "category": "Labrets",
    "body_parts": [
      "oreja"
    ],
    "price": 120.0,
    "sale_price": 115.9,
    "images": [
      "../static/img/products/labret/helix/5 cuerpos/blanco/foto 1 - 4.webp",
      "../static/img/products/labret/helix/5 cuerpos/blanco/foto 1 - 3.webp",
      "../static/img/products/labret/helix/5 cuerpos/blanco/foto 3 - 2.webp"
    ],
    "description": "Joya tipo Labret para piercing Helix hecha de Titanio Grado Implante con 5 gemas de Zircón Blanco incrustadas.",
    "is_new": true,
    "on_sale": false,
    "material": "titanio",
    "popularity": 0,
    "rosca": "interna",
    "id": 15
  }
]